LICENSE.md
NOTICE.md
README.md
setup.cfg
setup.py
bin/pgpkms
pgpkms/__init__.py
pgpkms/__main__.py
pgpkms/armour.py
pgpkms/pgpkms.py
pgpkms.egg-info/PKG-INFO
pgpkms.egg-info/SOURCES.txt
pgpkms.egg-info/dependency_links.txt
pgpkms.egg-info/requires.txt
pgpkms.egg-info/top_level.txt