Metadata-Version: 2.1
Name: pgpkms
Version: 1.0.5
Summary: PGP signatures with AWS KMS keys
Home-page: https://github.com/juitnow/pgpkms
Author: Juit Developers
Author-email: developers@juit.com
Maintainer: Juit Developers
Maintainer-email: developers@juit.com
License: Apache-2.0
Keywords: AWS,GnuPG,KMS,OpenPGP,PGP,RFC4880
Platform: UNKNOWN
Classifier: Topic :: Security
Classifier: Topic :: Security :: Cryptography
Classifier: Development Status :: 4 - Beta
Classifier: License :: OSI Approved :: Apache Software License
Classifier: Programming Language :: Python :: 3
Classifier: Intended Audience :: Developers
Classifier: Intended Audience :: System Administrators
Requires-Python: >=3.5
License-File: LICENSE.md
License-File: NOTICE.md
